<AML>
 <Item type="ItemType" id="BC7977377FFF40D59FF14205914E9C71" action="edit">
  <Relationships>
   <Item type="Morphae" id="DE32C8E3C356483A896D36443CB8A288" action="add">
    <related_id keyed_name="Project Task" type="ItemType" name="Project Task">9DC36DF7F0234A3E8CFFE2A20AB78CCE</related_id>
    <sort_order>256</sort_order>
    <source_id keyed_name="InBasket Task" type="ItemType" name="InBasket Task">BC7977377FFF40D59FF14205914E9C71</source_id>
   </Item>
  </Relationships>
 </Item>
</AML>