<AML>
 <Item type="Action" id="911254FCD77E4F4B8EAC5C140BD34705" action="add">
  <item_query>&lt;Item type="{@type}" id="{@id}" levels= "1" action="get" /&gt;</item_query>
  <label xml:lang="en">Transfer to SAP</label>
  <location>client</location>
  <method keyed_name="GAG_TransferToSAP" type="Method">
   <Item type="Method" action="get" select="id">
    <name>GAG_TransferToSAP</name>
   </Item>
  </method>
  <permission_id keyed_name="GAG_SAPTransfer" type="Permission">C942783BAAB84846B575D5309D18BFC3</permission_id>
  <target>none</target>
  <type>item</type>
  <name>GAG_SAPTransfer</name>
 </Item>
</AML>